lifecycles/__init__.py
lifecycles/filters.py
lifecycles/forms.py
lifecycles/models.py
lifecycles/navigation.py
lifecycles/tables.py
lifecycles/template_content.py
lifecycles/urls.py
lifecycles/urls.py.save
lifecycles/views.py
lifecycles/views.py.save
lifecycles/__pycache__/__init__.cpython-36.pyc
lifecycles/__pycache__/filters.cpython-36.pyc
lifecycles/__pycache__/forms.cpython-36.pyc
lifecycles/__pycache__/models.cpython-36.pyc
lifecycles/__pycache__/navigation.cpython-36.pyc
lifecycles/__pycache__/tables.cpython-36.pyc
lifecycles/__pycache__/template_content.cpython-36.pyc
lifecycles/__pycache__/urls.cpython-36.pyc
lifecycles/__pycache__/views.cpython-36.pyc
lifecycles/api/__init__.py
lifecycles/api/serializers.py
lifecycles/api/urls.py
lifecycles/api/views.py
lifecycles/api/__pycache__/__init__.cpython-36.pyc
lifecycles/api/__pycache__/serializers.cpython-36.pyc
lifecycles/api/__pycache__/urls.cpython-36.pyc
lifecycles/api/__pycache__/views.cpython-36.pyc
lifecycles/migrations/0001_initial.py
lifecycles/migrations/0002_auto_20200717_1506.py
lifecycles/migrations/0003_auto_20200717_1509.py
lifecycles/migrations/0004_auto_20200717_1625.py
lifecycles/migrations/0005_auto_20200722_1212.py
lifecycles/migrations/0006_auto_20200722_1253.py
lifecycles/migrations/0007_auto_20200722_1613.py
lifecycles/migrations/0008_auto_20200730_1616.py
lifecycles/migrations/__init__.py
lifecycles/migrations/__pycache__/0001_initial.cpython-36.pyc
lifecycles/migrations/__pycache__/0002_auto_20200717_1506.cpython-36.pyc
lifecycles/migrations/__pycache__/0003_auto_20200717_1509.cpython-36.pyc
lifecycles/migrations/__pycache__/0004_auto_20200717_1625.cpython-36.pyc
lifecycles/migrations/__pycache__/0005_auto_20200722_1212.cpython-36.pyc
lifecycles/migrations/__pycache__/0006_auto_20200722_1253.cpython-36.pyc
lifecycles/migrations/__pycache__/0007_auto_20200722_1613.cpython-36.pyc
lifecycles/migrations/__pycache__/0008_auto_20200730_1616.cpython-36.pyc
netbox_plugin_lifecycles-1.0.5.dist-info/LICENSE
netbox_plugin_lifecycles-1.0.5.dist-info/METADATA
netbox_plugin_lifecycles-1.0.5.dist-info/WHEEL
netbox_plugin_lifecycles-1.0.5.dist-info/top_level.txt
netbox_plugin_lifecycles-1.0.5.dist-info/RECORD
