Metadata-Version: 2.1
Name: netbox-plugin-lifecycles
Version: 1.0.5
Summary: Lifecycles for devices
Home-page: https://git.selectel.org/ogorov/netbox-lifecycles.git
Author: DCIM
Author-email: UNKNOWN
License: Apache 2.0
Platform: UNKNOWN
